MemePy/MemeFactory.py
MemePy/MemeGenerator.py
MemePy/MemeLibJsonDecoder.py
MemePy/MemeModel.py
MemePy/__init__.py
MemePy/__main__.py
MemePy/definitions.py
MemePy/Resources/FontLibrary/BLKCHCRY.TTF
MemePy/Resources/FontLibrary/arial.ttf
MemePy/Resources/FontLibrary/impact.ttf
MemePy/Resources/ImageLibrary/balloon.jpg
MemePy/Resources/ImageLibrary/bellcurve.jpg
MemePy/Resources/ImageLibrary/butgodsaid.jpg
MemePy/Resources/ImageLibrary/classnote.png
MemePy/Resources/ImageLibrary/classy.jpg
MemePy/Resources/ImageLibrary/cliff.jpg
MemePy/Resources/ImageLibrary/cola.jpg
MemePy/Resources/ImageLibrary/finally.jpg
MemePy/Resources/ImageLibrary/handshake.gif
MemePy/Resources/ImageLibrary/hate.png
MemePy/Resources/ImageLibrary/headache.png
MemePy/Resources/ImageLibrary/itsretarded.png
MemePy/Resources/ImageLibrary/itstime.png
MemePy/Resources/ImageLibrary/knight.png
MemePy/Resources/ImageLibrary/lookup.gif
MemePy/Resources/ImageLibrary/loud.jpg
MemePy/Resources/ImageLibrary/mealsome.png
MemePy/Resources/ImageLibrary/milking.jpg
MemePy/Resources/ImageLibrary/nutbutton.jpg
MemePy/Resources/ImageLibrary/pills.jpg
MemePy/Resources/ImageLibrary/tradeoffer.gif
MemePy/Resources/ImageLibrary/tradeoffer.jpg
MemePy/Resources/ImageLibrary/trump.jpg
MemePy/Resources/ImageLibrary/vape.png
MemePy/Resources/ImageLibrary/yeshoney.jpg
MemePy/Resources/MemeLibrary/builtin.JSON
memepy-1.2.4.dist-info/licenses/LICENSE
memepy-1.2.4.dist-info/METADATA
memepy-1.2.4.dist-info/WHEEL
memepy-1.2.4.dist-info/top_level.txt
memepy-1.2.4.dist-info/RECORD
