Metadata-Version: 2.4
Name: MemePy
Version: 1.2.4
Summary: Meme Generator for python
Home-page: https://github.com/julianbrandt/MemePy
Author: Julian Brandt
Author-email: julian@julianbrandt.dk
License: MIT
Classifier: Programming Language :: Python :: 3
Classifier: License :: OSI Approved :: MIT License
Classifier: Operating System :: OS Independent
License-File: LICENSE
Requires-Dist: pillow~=8.4
Requires-Dist: requests~=2.32
Dynamic: author
Dynamic: author-email
Dynamic: classifier
Dynamic: description
Dynamic: description-content-type
Dynamic: home-page
Dynamic: license
Dynamic: license-file
Dynamic: requires-dist
Dynamic: summary
